goldfinder/__init__.py
goldfinder/goldfinder.py
goldfinder/misc.py
goldfinder-1.3.0.dist-info/DESCRIPTION.rst
goldfinder-1.3.0.dist-info/METADATA
goldfinder-1.3.0.dist-info/RECORD
goldfinder-1.3.0.dist-info/WHEEL
goldfinder-1.3.0.dist-info/entry_points.txt
goldfinder-1.3.0.dist-info/metadata.json
goldfinder-1.3.0.dist-info/top_level.txt
